d2.py
d2-0.7.dist-info/METADATA
d2-0.7.dist-info/WHEEL
d2-0.7.dist-info/entry_points.txt
d2-0.7.dist-info/top_level.txt
d2-0.7.dist-info/RECORD
