Metadata-Version: 2.1
Name: d2
Version: 0.7
Summary: CLI to get API JSON data and show as table
Home-page: https://github.com/weaming/d2
Author: weaming
Author-email: garden.yuen@gmail.com
License: UNKNOWN
Project-URL: Source, https://github.com/weaming/d2
Project-URL: Bug Reports, https://github.com/weaming/d2
Keywords: tools,api
Platform: UNKNOWN
Requires-Dist: requests
Requires-Dist: tabulate
